buildflaskapp/__init__.py
buildflaskapp/buildflaskapp.py
buildflaskapp/scripts/__init__.py
buildflaskapp/scripts/__version__.py
buildflaskapp/scripts/manual.py
buildflaskapp/scripts/messages.py
buildflaskapp/scripts/workflow.py
buildflaskapp-0.3.5.dist-info/LICENSE
buildflaskapp-0.3.5.dist-info/METADATA
buildflaskapp-0.3.5.dist-info/WHEEL
buildflaskapp-0.3.5.dist-info/entry_points.txt
buildflaskapp-0.3.5.dist-info/top_level.txt
buildflaskapp-0.3.5.dist-info/RECORD
