Metadata-Version: 2.1
Name: buildflaskapp
Version: 0.3.5
Summary: A flask app generator package
Home-page: https://github.com/askyourkode/buildflaskapp
Author: Hans Maulloo
Author-email: maulloohans@gmail.com
License: UNKNOWN
Platform: UNKNOWN
Classifier: Development Status :: 2 - Pre-Alpha
Classifier: Framework :: Flask
Classifier: Intended Audience :: Developers
Classifier: Programming Language :: Python :: 3
Classifier: License :: Freely Distributable
Classifier: Operating System :: Microsoft :: Windows
Classifier: Operating System :: POSIX :: Linux
Classifier: Topic :: Software Development :: Code Generators
Requires-Dist: tabulate
